CITATION.cff
CODE_OF_CONDUCT.md
CONTRIBUTING.md
LICENSE.md
MANIFEST.in
README.md
setup.py
hypercontagion/__init__.py
hypercontagion/exception.py
hypercontagion.egg-info/PKG-INFO
hypercontagion.egg-info/SOURCES.txt
hypercontagion.egg-info/dependency_links.txt
hypercontagion.egg-info/requires.txt
hypercontagion.egg-info/top_level.txt
hypercontagion/sim/__init__.py
hypercontagion/sim/epidemics.py
hypercontagion/sim/functions.py
hypercontagion/sim/opinions.py
hypercontagion/utils/__init__.py
hypercontagion/utils/utilities.py
hypercontagion/visualization/__init__.py
hypercontagion/visualization/animation.py
requirements/default.txt
requirements/developer.txt
requirements/documentation.txt
requirements/release.txt
requirements/test.txt
requirements/tutorial.txt
tutorials/tutorial_1_epidemic_modeling.ipynb
tutorials/tutorial_2_opinion_formation_modeling.ipynb
tutorials/tutorial_3_animations.ipynb