Metadata-Version: 2.1
Name: hypercontagion
Version: 0.1.2
Summary: HyperContagion is a Python library for the simulation of contagion on complex systems with group (higher-order) interactions.
Home-page: https://github.com/nwlandry/hypercontagion
Author: Nicholas Landry
Author-email: nicholas.landry@colorado.edu
Provides-Extra: developer
Provides-Extra: documentation
Provides-Extra: release
Provides-Extra: test
Provides-Extra: tutorial
License-File: LICENSE.md
